README.rst
setup.py
yaque_tts/__init__.py
yaque_tts/audio_play.py
yaque_tts/main.py
yaque_tts/read_audio.py
yaque_tts/read_word_index.py
yaque_tts/yaque_tts.py
yaque_tts.egg-info/PKG-INFO
yaque_tts.egg-info/SOURCES.txt
yaque_tts.egg-info/dependency_links.txt
yaque_tts.egg-info/entry_points.txt
yaque_tts.egg-info/requires.txt
yaque_tts.egg-info/top_level.txt