Metadata-Version: 1.1
Name: yaque-tts
Version: 0.0.2
Summary: 一个简单的，仅仅支持中文的tts模块
Home-page: http://www.wdiannao.com
Author: yaquepeng
Author-email: yaquepeng@outlook.com
License: UNKNOWN
Platform: UNKNOWN
Classifier: Operating System :: OS Independent
Classifier: Intended Audience :: Developers
Classifier: Programming Language :: Python
Classifier: Programming Language :: Python :: Implementation
Classifier: Programming Language :: Python :: 2.7
